punjabi_verb_forms/__init__.py
punjabi_verb_forms/inflector.py
punjabi_verb_forms-0.1.0.dist-info/licenses/LICENSE
punjabi_verb_forms-0.1.0.dist-info/METADATA
punjabi_verb_forms-0.1.0.dist-info/WHEEL
punjabi_verb_forms-0.1.0.dist-info/top_level.txt
punjabi_verb_forms-0.1.0.dist-info/RECORD
