Metadata-Version: 2.4
Name: punjabi-verb-forms
Version: 0.1.0
Summary: Punjabi verb form inflection using root words and suffixes
Home-page: https://github.com/yourusername/punjabi-verb-forms
Author: Your Name
Author-email: Your Name <your@email.com>
License: MIT
Project-URL: Homepage, https://github.com/MuhammadshoaibTahir/punjabi-verb-forms
Requires-Python: >=3.6
License-File: LICENSE
Dynamic: author
Dynamic: home-page
Dynamic: license-file
Dynamic: requires-python
